neml2/__init__.py
neml2/base.cpython-39-x86_64-linux-gnu.so
neml2/include/hit/braceexpr.h
neml2/include/hit/hit.h
neml2/include/hit/lex.h
neml2/include/hit/parse.h
neml2/include/neml2/base/CrossRef.h
neml2/include/neml2/base/DependencyDefinition.h
neml2/include/neml2/base/DependencyResolver.h
neml2/include/neml2/base/Factory.h
neml2/include/neml2/base/HITParser.h
neml2/include/neml2/base/NEML2Object.h
neml2/include/neml2/base/OptionCollection.h
neml2/include/neml2/base/OptionSet.h
neml2/include/neml2/base/Parser.h
neml2/include/neml2/base/Registry.h
neml2/include/neml2/base/Storage.h
neml2/include/neml2/base/config.h
neml2/include/neml2/drivers/Driver.h
neml2/include/neml2/drivers/TransientDriver.h
neml2/include/neml2/drivers/solid_mechanics/LargeDeformationIncrementalSolidMechanicsDriver.h
neml2/include/neml2/drivers/solid_mechanics/SolidMechanicsDriver.h
neml2/include/neml2/misc/error.h
neml2/include/neml2/misc/math.h
neml2/include/neml2/misc/parser_utils.h
neml2/include/neml2/misc/types.h
neml2/include/neml2/misc/utils.h
neml2/include/neml2/models/BackwardEulerTimeIntegration.h
neml2/include/neml2/models/BufferStore.h
neml2/include/neml2/models/ComposedModel.h
neml2/include/neml2/models/Data.h
neml2/include/neml2/models/ForceRate.h
neml2/include/neml2/models/ForwardEulerTimeIntegration.h
neml2/include/neml2/models/ImplicitUpdate.h
neml2/include/neml2/models/Interpolation.h
neml2/include/neml2/models/LinearInterpolation.h
neml2/include/neml2/models/Model.h
neml2/include/neml2/models/NonlinearParameter.h
neml2/include/neml2/models/ParameterStore.h
neml2/include/neml2/models/RotationMatrix.h
neml2/include/neml2/models/SR2Invariant.h
neml2/include/neml2/models/StateRate.h
neml2/include/neml2/models/SumModel.h
neml2/include/neml2/models/VariableStore.h
neml2/include/neml2/models/WR2ExplicitExponentialTimeIntegration.h
neml2/include/neml2/models/WR2ImplicitExponentialTimeIntegration.h
neml2/include/neml2/models/crystallography/CrystalGeometry.h
neml2-1.3.1.dist-info/METADATA
neml2-1.3.1.dist-info/WHEEL
neml2-1.3.1.dist-info/entry_points.txt
neml2-1.3.1.dist-info/licenses/LICENSE
neml2-1.3.1.dist-info/RECORD
