Metadata-Version: 2.1
Name: neml2
Version: 1.3.1
Summary: GPU-enabled vectorized material modeling library
Author-Email: Mark Messner <messner@anl.gov>, Gary Hu <thu@anl.gov>
Requires-Python: >=3.8
Requires-Dist: torch==2.2.1
License-File: LICENSE
